{
    "type": "FeatureCollection",
    "features": [
        {
            "type": "Feature",
            "properties": {
                "grid_id": "G18860960",
                "placemark_id": "",
                "market": "Anvik",
                "number": 1,
                "population": 2,
                "area": 17390.61,
                "road_meters": 216,
                "frame": "2 - Microwave LTE",
                "downlink": 9994.21,
                "uplink": 696.17,
                "umts": 0,
                "gsm": 0
            },
            "geometry": {
                "type": "Polygon",
                "coordinates": [
                    [
                        [
                            -160.223489502949,
                            62.6357611392706
                        ],
                        [
                            -160.226528916118,
                            62.6445641788988
                        ],
                        [
                            -160.207132190053,
                            62.6459427585746
                        ],
                        [
                            -160.204098355334,
                            62.6371393119916
                        ],
                        [
                            -160.223489502949,
                            62.6357611392706
                        ]
                    ]
                ]
            }
        },
        {
            "type": "Feature",
            "properties": {
                "grid_id": "G18860961",
                "placemark_id": "",
                "market": "Anvik",
                "number": 2,
                "population": 2.97,
                "area": 25719.12,
                "road_meters": 167,
                "frame": "2 - Microwave LTE",
                "downlink": 83562.62,
                "uplink": 2616.28,
                "umts": 0,
                "gsm": 0
            },
            "geometry": {
                "type": "Polygon",
                "coordinates": [
                    [
                        [
                            -160.226528916118,
                            62.6445641788988
                        ],
                        [
                            -160.229570122441,
                            62.6533671581305
                        ],
                        [
                            -160.2101678148,
                            62.6547461450332
                        ],
                        [
                            -160.207132190053,
                            62.6459427585746
                        ],
                        [
                            -160.226528916118,
                            62.6445641788988
                        ]
                    ]
                ]
            }
        },
        {
            "type": "Feature",
            "properties": {
                "grid_id": "G18860962",
                "placemark_id": "",
                "market": "Anvik",
                "number": 3,
                "population": 2.42,
                "area": 22712.86,
                "road_meters": 339,
                "frame": "2 - Microwave LTE",
                "downlink": 260986.53,
                "uplink": 6861.64,
                "umts": 0,
                "gsm": 0
            },
            "geometry": {
                "type": "Polygon",
                "coordinates": [
                    [
                        [
                            -160.229570122441,
                            62.6533671581305
                        ],
                        [
                            -160.232613123494,
                            62.6621700771322
                        ],
                        [
                            -160.213205231148,
                            62.663549471534
                        ],
                        [
                            -160.2101678148,
                            62.6547461450332
                        ],
                        [
                            -160.229570122441,
                            62.6533671581305
                        ]
                    ]
                ]
            }
        },
        {
            "type": "Feature",
            "properties": {
                "grid_id": "G18870960",
                "placemark_id": "",
                "market": "Anvik",
                "number": 4,
                "population": 1.15,
                "area": 9838.32,
                "road_meters": 1376,
                "frame": "2 - Microwave LTE",
                "downlink": 51799.3,
                "uplink": 2909.77,
                "umts": 0,
                "gsm": 0
            },
            "geometry": {
                "type": "Polygon",
                "coordinates": [
                    [
                        [
                            -160.204098355334,
                            62.6371393119916
                        ],
                        [
                            -160.207132190053,
                            62.6459427585746
                        ],
                        [
                            -160.18773367396,
                            62.6473187419962
                        ],
                        [
                            -160.184705419262,
                            62.6385148891819
                        ],
                        [
                            -160.204098355334,
                            62.6371393119916
                        ]
                    ]
                ]
            }
        },
        {
            "type": "Feature",
            "properties": {
                "grid_id": "G18870961",
                "placemark_id": "",
                "market": "Anvik",
                "number": 5,
                "population": 64.34,
                "area": 550008.43,
                "road_meters": 4860,
                "frame": "2 - Microwave LTE",
                "downlink": 321364.72,
                "uplink": 7862.08,
                "umts": 0,
                "gsm": 0
            },
            "geometry": {
                "type": "Polygon",
                "coordinates": [
                    [
                        [
                            -160.207132190053,
                            62.6459427585746
                        ],
                        [
                            -160.2101678148,
                            62.6547461450332
                        ],
                        [
                            -160.190763715559,
                            62.6561225349576
                        ],
                        [
                            -160.18773367396,
                            62.6473187419962
                        ],
                        [
                            -160.207132190053,
                            62.6459427585746
                        ]
                    ]
                ]
            }
        },
        {
            "type": "Feature",
            "properties": {
                "grid_id": "G18870962",
                "placemark_id": "",
                "market": "Anvik",
                "number": 6,
                "population": 5.74,
                "area": 49097.37,
                "road_meters": 1967,
                "frame": "2 - Microwave LTE",
                "downlink": 35374.28,
                "uplink": 1326.27,
                "umts": 0,
                "gsm": 0
            },
            "geometry": {
                "type": "Polygon",
                "coordinates": [
                    [
                        [
                            -160.2101678148,
                            62.6547461450332
                        ],
                        [
                            -160.213205231148,
                            62.663549471534
                        ],
                        [
                            -160.193795545629,
                            62.6649262682331
                        ],
                        [
                            -160.190763715559,
                            62.6561225349576
                        ],
                        [
                            -160.2101678148,
                            62.6547461450332
                        ]
                    ]
                ]
            }
        },
        {
            "type": "Feature",
            "properties": {
                "grid_id": "G18880961",
                "placemark_id": "",
                "market": "Anvik",
                "number": 7,
                "population": 5.19,
                "area": 44356.85,
                "road_meters": 1560,
                "frame": "2 - Microwave LTE",
                "downlink": 10812.9,
                "uplink": 933.81,
                "umts": 0,
                "gsm": 0
            },
            "geometry": {
                "type": "Polygon",
                "coordinates": [
                    [
                        [
                            -160.18773367396,
                            62.6473187419962
                        ],
                        [
                            -160.190763715559,
                            62.6561225349576
                        ],
                        [
                            -160.171357827848,
                            62.6574963275449
                        ],
                        [
                            -160.168333370966,
                            62.6486921288049
                        ],
                        [
                            -160.18773367396,
                            62.6473187419962
                        ]
                    ]
                ]
            }
        }
    ]
}
